cuallee/__init__.py
cuallee/bigquery_validation.py
cuallee/daft_validation.py
cuallee/duckdb_validation.py
cuallee/pandas_validation.py
cuallee/polars_validation.py
cuallee/pyspark_validation.py
cuallee/snowpark_validation.py
cuallee/utils.py
cuallee/bio/__init__.py
cuallee/bio/amino_acids.csv
cuallee/bio/checks.py
cuallee/cloud/__init__.py
cuallee/dagster/__init__.py
cuallee/iso/__init__.py
cuallee/iso/checks.py
cuallee/logic/__init__.py
cuallee/report/__init__.py
cuallee-0.15.4.dist-info/licenses/LICENSE
cuallee-0.15.4.dist-info/METADATA
cuallee-0.15.4.dist-info/WHEEL
cuallee-0.15.4.dist-info/top_level.txt
cuallee-0.15.4.dist-info/RECORD
