Metadata-Version: 2.4
Name: cuallee
Version: 0.15.4
Summary: Python library for data validation on DataFrame APIs including Snowflake/Snowpark, Apache/PySpark and Pandas/DataFrame.
Author-email: Herminio Vazquez <canimus@gmail.com>, Virginie Grosboillot <vestalisvirginis@gmail.com>
License:                                  Apache License
Project-URL: Homepage, https://github.com/canimus/cuallee
Project-URL: Bug Tracker, https://github.com/canimus/cuallee
Classifier: Programming Language :: Python :: 3
Classifier: Operating System :: OS Independent
Requires-Python: >=3.10
License-File: LICENSE
Requires-Dist: toolz>=0.12.1
Requires-Dist: requests>=2.28
Provides-Extra: dev
Requires-Dist: black==25.1.0; extra == "dev"
Requires-Dist: ruff==0.9.10; extra == "dev"
Requires-Dist: pre-commit==4.1.0; extra == "dev"
Provides-Extra: pyspark
Requires-Dist: pyspark>=3.4.0; extra == "pyspark"
Provides-Extra: pyspark-connect
Requires-Dist: pyspark[connect]; extra == "pyspark-connect"
Provides-Extra: snowpark
Requires-Dist: snowflake-snowpark-python==1.11.1; extra == "snowpark"
Requires-Dist: pyarrow>=14.0.2; extra == "snowpark"
Provides-Extra: pandas
Requires-Dist: pandas>=2.0.1; extra == "pandas"
Provides-Extra: bigquery
Requires-Dist: google-cloud-bigquery>=3.10.0; extra == "bigquery"
Requires-Dist: pyarrow>=11.0.0; extra == "bigquery"
Provides-Extra: duckdb
Requires-Dist: duckdb==1.2.0; extra == "duckdb"
Provides-Extra: polars
Requires-Dist: polars>=1.8.2; extra == "polars"
Provides-Extra: test
Requires-Dist: pytest; extra == "test"
Requires-Dist: pytest-cov; extra == "test"
Requires-Dist: pendulum>=2.1.2; extra == "test"
Provides-Extra: dagster
Requires-Dist: dagster==1.9.5; extra == "dagster"
Provides-Extra: cloud
Requires-Dist: msgpack==1.1.0; extra == "cloud"
Provides-Extra: pdf
Requires-Dist: fpdf2==2.8.2; extra == "pdf"
Provides-Extra: daft
Requires-Dist: getdaft==0.3.4; extra == "daft"
Provides-Extra: all
Requires-Dist: cuallee[bigquery,cloud,daft,dagster,dev,duckdb,pandas,pdf,polars,pyspark,pyspark_connect,snowpark,test]; extra == "all"
Dynamic: license-file
